epub_cfi_toolkit/__init__.py
epub_cfi_toolkit/cfi_parser.py
epub_cfi_toolkit/cfi_processor.py
epub_cfi_toolkit/cfi_validator.py
epub_cfi_toolkit/epub_parser.py
epub_cfi_toolkit/exceptions.py
epub_cfi_toolkit-0.1.0.dist-info/licenses/LICENSE
epub_cfi_toolkit-0.1.0.dist-info/METADATA
epub_cfi_toolkit-0.1.0.dist-info/WHEEL
epub_cfi_toolkit-0.1.0.dist-info/top_level.txt
epub_cfi_toolkit-0.1.0.dist-info/RECORD
