Metadata-Version: 2.4
Name: epub-cfi-toolkit
Version: 0.1.0
Summary: A Python toolkit for processing EPUB Canonical Fragment Identifiers (CFIs)
Author-email: PagePal <info@pagepalapp.com>
Maintainer-email: PagePal <info@pagepalapp.com>
License: MIT
Project-URL: Homepage, https://github.com/PagePalApp/epub-cfi-toolkit
Project-URL: Repository, https://github.com/PagePalApp/epub-cfi-toolkit
Project-URL: Issues, https://github.com/PagePalApp/epub-cfi-toolkit/issues
Keywords: epub,cfi,ebook,canonical-fragment-identifier
Classifier: Development Status :: 3 - Alpha
Classifier: Intended Audience :: Developers
Classifier: License :: OSI Approved :: MIT License
Classifier: Programming Language :: Python :: 3
Classifier: Programming Language :: Python :: 3.8
Classifier: Programming Language :: Python :: 3.9
Classifier: Programming Language :: Python :: 3.10
Classifier: Programming Language :: Python :: 3.11
Classifier: Programming Language :: Python :: 3.12
Classifier: Topic :: Software Development :: Libraries :: Python Modules
Classifier: Topic :: Text Processing :: Markup :: XML
Requires-Python: >=3.8
License-File: LICENSE
Requires-Dist: lxml>=4.6.0
Provides-Extra: dev
Requires-Dist: pytest>=7.0; extra == "dev"
Requires-Dist: pytest-cov>=4.0; extra == "dev"
Requires-Dist: black>=22.0; extra == "dev"
Requires-Dist: isort>=5.0; extra == "dev"
Requires-Dist: flake8>=4.0; extra == "dev"
Requires-Dist: mypy>=1.0; extra == "dev"
Dynamic: license-file
